classifyawsetsjsonbyregion/__init__.py
classifyawsetsjsonbyregion/analyzer.py
classifyawsetsjsonbyregion/awsets.py
classifyawsetsjsonbyregion/cli.py
classifyawsetsjsonbyregion/config.py
classifyawsetsjsonbyregion/csv.py
classifyawsetsjsonbyregion/filepath.py
classifyawsetsjsonbyregion/py.typed
classifyawsetsjsonbyregion/awsregion/__init__.py
classifyawsetsjsonbyregion/awsregion/classifier.py
classifyawsetsjsonbyregion-0.1.0.dist-info/LICENSE
classifyawsetsjsonbyregion-0.1.0.dist-info/METADATA
classifyawsetsjsonbyregion-0.1.0.dist-info/WHEEL
classifyawsetsjsonbyregion-0.1.0.dist-info/entry_points.txt
classifyawsetsjsonbyregion-0.1.0.dist-info/top_level.txt
classifyawsetsjsonbyregion-0.1.0.dist-info/RECORD
