Metadata-Version: 2.1
Name: classifyawsetsjsonbyregion
Version: 0.1.0
Summary: Classifies AWSets JSON by region.
Author-email: Yukihiko Shinoda <yuk.hik.future@gmail.com>
Maintainer-email: Yukihiko Shinoda <yuk.hik.future@gmail.com>
License: MIT License
Project-URL: homepage, https://github.com/yukihiko-shinoda/classify-awsets-json-by-region
Project-URL: repository, https://github.com/yukihiko-shinoda/classify-awsets-json-by-region
Keywords: classifyawsetsjsonbyregion,classify-awsets-json-by-region,awsets,aws
Classifier: Development Status :: 4 - Beta
Classifier: Intended Audience :: Developers
Classifier: Intended Audience :: Information Technology
Classifier: License :: OSI Approved :: MIT License
Classifier: Natural Language :: English
Classifier: Operating System :: OS Independent
Classifier: Programming Language :: Python
Classifier: Programming Language :: Python :: 3
Classifier: Programming Language :: Python :: 3.7
Classifier: Programming Language :: Python :: 3.8
Classifier: Programming Language :: Python :: 3.9
Classifier: Programming Language :: Python :: 3.10
Classifier: Programming Language :: Python :: 3.11
Classifier: Topic :: Scientific/Engineering
Classifier: Topic :: Scientific/Engineering :: Information Analysis
Classifier: Topic :: Security
Classifier: Topic :: Text Processing
Classifier: Topic :: Text Processing :: Filters
Classifier: Typing :: Typed
Requires-Python: >=3.7
License-File: LICENSE
Requires-Dist: click (>=7.0)
Requires-Dist: yamldataclassconfig
Requires-Dist: typing-extensions ; python_version <= "3.7"
Provides-Extra: test
